gerobust
