Metadata-Version: 1.1
Name: gerobust
Version: 0.4.0
Summary: Extension in C for incircles tests (2D/3D)
Home-page: https://github.com/aluriak/gerobust
Author: lucas bourneuf
Author-email: lucas.bourneuf@openmailbox.org
License: UNKNOWN
Keywords: C function robust geometry
Platform: UNKNOWN
Classifier: Development Status :: 2 - Pre-Alpha
Classifier: Intended Audience :: Science/Research
Classifier: License :: OSI Approved :: GNU General Public License (GPL)
Classifier: Natural Language :: English
Classifier: Programming Language :: C
Classifier: Programming Language :: Python :: 3
Classifier: Topic :: Software Development :: Libraries :: Python Modules
